django_firewall/__init__.py
django_firewall/admin.py
django_firewall/apps.py
django_firewall/conf.py
django_firewall/endpoint_list.py
django_firewall/helpers.py
django_firewall/middleware.py
django_firewall/models.py
django_firewall/serializers.py
django_firewall/tests.py
django_firewall/urls.py
django_firewall/views.py
django_firewall/bin/get_firewall_host.sh
django_firewall/management/__init__.py
django_firewall/management/commands/__init__.py
django_firewall/management/commands/firewall.py
django_firewall/management/commands/import_firewall_rules.py
django_firewall/migrations/0001_initial.py
django_firewall/migrations/0002_rename_django_fire_remote__idx_django_fire_remote__1d8092_idx_and_more.py
django_firewall/migrations/0003_firewallpathrule.py
django_firewall/migrations/__init__.py
django_firewall-2.0.3.dist-info/licenses/LICENSE
django_firewall-2.0.3.dist-info/METADATA
django_firewall-2.0.3.dist-info/WHEEL
django_firewall-2.0.3.dist-info/top_level.txt
django_firewall-2.0.3.dist-info/RECORD
