Metadata-Version: 2.4
Name: django-firewall
Version: 2.0.3
Summary: IP-based firewall protection for Django with path rule management.
Author: Visian Systems
License-Expression: MIT
Project-URL: Homepage, https://visiansystems.com
Classifier: Development Status :: 4 - Beta
Classifier: Framework :: Django
Classifier: Framework :: Django :: 4.2
Classifier: Framework :: Django :: 5.2
Classifier: Intended Audience :: Developers
Classifier: Programming Language :: Python :: 3
Classifier: Programming Language :: Python :: 3 :: Only
Classifier: Programming Language :: Python :: 3.10
Classifier: Programming Language :: Python :: 3.11
Classifier: Programming Language :: Python :: 3.12
Classifier: Programming Language :: Python :: 3.13
Classifier: Topic :: Internet :: WWW/HTTP
Classifier: Topic :: Security
Requires-Python: >=3.10
License-File: LICENSE
Requires-Dist: Django<5.2,>=4.2
Requires-Dist: requests>=2.28
Provides-Extra: rest
Requires-Dist: djangorestframework>=3.14; extra == "rest"
Dynamic: license-file
